netimate/__init__.py
netimate/__main__.py
netimate/composition.py
netimate/application/__init__.py
netimate/application/application.py
netimate/application/command_executor_service.py
netimate/application/snapshot_service.py
netimate/core/__init__.py
netimate/core/runner.py
netimate/core/plugin_engine/__init__.py
netimate/core/plugin_engine/loader.py
netimate/core/plugin_engine/plugin_registry.py
netimate/core/plugin_engine/registrar.py
netimate/errors/__init__.py
netimate/errors/application.py
netimate/errors/base.py
netimate/errors/cli.py
netimate/errors/command.py
netimate/errors/config.py
netimate/errors/connection.py
netimate/errors/registry.py
netimate/errors/runner.py
netimate/errors/shell.py
netimate/infrastructure/__init__.py
netimate/infrastructure/config_loader.py
netimate/infrastructure/logging.py
netimate/infrastructure/settings.py
netimate/infrastructure/template_provider/__init__.py
netimate/infrastructure/template_provider/filesystem.py
netimate/infrastructure/utils/__init__.py
netimate/infrastructure/utils/file_management.py
netimate/interfaces/__init__.py
netimate/interfaces/application/__init__.py
netimate/interfaces/application/application.py
netimate/interfaces/core/__init__.py
netimate/interfaces/core/registry.py
netimate/interfaces/core/runner.py
netimate/interfaces/infrastructure/__init__.py
netimate/interfaces/infrastructure/settings.py
netimate/interfaces/infrastructure/template_provider.py
netimate/interfaces/plugin/__init__.py
netimate/interfaces/plugin/connection_protocol.py
netimate/interfaces/plugin/device_command.py
netimate/interfaces/plugin/device_repository.py
netimate/interfaces/plugin/plugin.py
netimate/models/__init__.py
netimate/models/device.py
netimate/plugins/__init__.py
netimate/plugins/connection_protocols/__init__.py
netimate/plugins/connection_protocols/netmiko/__init__.py
netimate/plugins/connection_protocols/netmiko/ssh.py
netimate/plugins/connection_protocols/netmiko/telnet.py
netimate-0.5.0.dist-info/licenses/LICENSE
netimate-0.5.0.dist-info/METADATA
netimate-0.5.0.dist-info/WHEEL
netimate-0.5.0.dist-info/entry_points.txt
netimate-0.5.0.dist-info/top_level.txt
netimate-0.5.0.dist-info/RECORD
