Metadata-Version: 2.4
Name: netimate
Version: 0.5.0
Summary: A lightweight, async-first network automation toolkit with plugin support and a rich CLI/shell interface.
Author-email: Simon Di Giovanni <s.digiovanni92@gmail.com>
License: MPL-2.0
Project-URL: Homepage, https://github.com/sjdigiovanni/netimate
Project-URL: Repository, https://github.com/sjdigiovanni/netimate
Project-URL: Documentation, https://github.com/sjdigiovanni/netimate#readme
Project-URL: Issues, https://github.com/sjdigiovanni/netimate/issues
Keywords: network automation,async,cli,scrapli,netmiko,diff,snapshot,devops
Classifier: Development Status :: 4 - Beta
Classifier: Intended Audience :: System Administrators
Classifier: Intended Audience :: Developers
Classifier: Intended Audience :: Telecommunications Industry
Classifier: License :: OSI Approved :: Mozilla Public License 2.0 (MPL 2.0)
Classifier: Programming Language :: Python :: 3
Classifier: Programming Language :: Python :: 3.9
Classifier: Programming Language :: Python :: 3.10
Classifier: Programming Language :: Python :: 3.11
Classifier: Programming Language :: Python :: 3.12
Classifier: Programming Language :: Python :: 3.13
Classifier: Topic :: System :: Networking
Classifier: Topic :: Utilities
Classifier: Typing :: Typed
Requires-Python: >=3.9
License-File: LICENSE
Requires-Dist: netmiko>=4.5.0
Requires-Dist: pyyaml>=6.0.2
Requires-Dist: scrapli>=2025.1.30
Requires-Dist: rich>=14.0.0
Requires-Dist: textfsm>=1.1.3
Requires-Dist: ttp>=0.9.5
Requires-Dist: psycopg2-binary
Requires-Dist: asyncssh
Requires-Dist: anyio
Requires-Dist: prompt-toolkit
Provides-Extra: test
Requires-Dist: pytest>=8.3.5; extra == "test"
Requires-Dist: pytest-asyncio; extra == "test"
Requires-Dist: pytest-cov; extra == "test"
Requires-Dist: black; extra == "test"
Requires-Dist: ruff; extra == "test"
Requires-Dist: radon; extra == "test"
Requires-Dist: import-linter; extra == "test"
Requires-Dist: mypy; extra == "test"
Requires-Dist: types-PyYAML; extra == "test"
Requires-Dist: types-toml; extra == "test"
Dynamic: license-file
